fitr/__init__.py
fitr/fitr.py
fitr/loglik_functions.py
fitr/model_selection.py
fitr/rlparams.py
fitr/tasks.py
fitr/utils.py
fitr-0.0.0.dev1.dist-info/DESCRIPTION.rst
fitr-0.0.0.dev1.dist-info/METADATA
fitr-0.0.0.dev1.dist-info/RECORD
fitr-0.0.0.dev1.dist-info/WHEEL
fitr-0.0.0.dev1.dist-info/metadata.json
fitr-0.0.0.dev1.dist-info/top_level.txt
