Metadata-Version: 2.0
Name: fitr
Version: 0.0.0.dev1
Summary: Fit reinforcement learning models to behavioural data
Home-page: https://github.com/ComputationalPsychiatry/fitr
Author: Abraham Nunes
Author-email: nunes@dal.ca
License: MIT
Keywords: reinforcement learning,computational psychiatry,python,model fitting
Platform: UNKNOWN
Classifier: Development Status :: 1 - Planning
Classifier: Intended Audience :: Science/Research
Classifier: Topic :: Scientific/Engineering
Classifier: Topic :: Scientific/Engineering :: Artificial Intelligence
Classifier: Topic :: Scientific/Engineering :: Medical Science Apps.
Classifier: License :: OSI Approved :: MIT License
Classifier: Programming Language :: Python :: 3.5
Classifier: Programming Language :: Python :: 2.7
